xxpop/__init__.py
xxpop-0.0.2.dist-info/LICENSE
xxpop-0.0.2.dist-info/METADATA
xxpop-0.0.2.dist-info/WHEEL
xxpop-0.0.2.dist-info/top_level.txt
xxpop-0.0.2.dist-info/RECORD
